purplship/mappers/purolator/__init__.py
purplship/mappers/purolator/mapper.py
purplship/mappers/purolator/proxy.py
purplship/mappers/purolator/settings.py
purplship/providers/purolator/__init__.py
purplship/providers/purolator/address.py
purplship/providers/purolator/error.py
purplship/providers/purolator/pickup/__init__.py
purplship/providers/purolator/pickup/cancel.py
purplship/providers/purolator/pickup/create.py
purplship/providers/purolator/pickup/update.py
purplship/providers/purolator/pickup/validate.py
purplship/providers/purolator/rate.py
purplship/providers/purolator/shipment/__init__.py
purplship/providers/purolator/shipment/cancel.py
purplship/providers/purolator/shipment/create.py
purplship/providers/purolator/shipment/documents.py
purplship/providers/purolator/tracking.py
purplship/providers/purolator/units.py
purplship/providers/purolator/utils.py
purplship.purolator-2022.2.dist-info/WHEEL
purplship.purolator-2022.2.dist-info/METADATA
purplship.purolator-2022.2.dist-info/RECORD
